githsearch-0.1.1.dist-info/DESCRIPTION.rst
githsearch-0.1.1.dist-info/entry_points.txt
githsearch-0.1.1.dist-info/METADATA
githsearch-0.1.1.dist-info/RECORD
githsearch-0.1.1.dist-info/top_level.txt
githsearch-0.1.1.dist-info/metadata.json
githsearch-0.1.1.dist-info/WHEEL
githsearch/__init__.py
githsearch/githsearch.py
