Metadata-Version: 2.0
Name: githsearch
Version: 0.1.1
Summary: Search Github from the command line, the quick and dirty way
Home-page: https://github.com/bayang/githsearch
Author: bayang
Author-email: wabayang@gmail.com
License: WTFPL
Keywords: search github command-line
Platform: UNKNOWN
Classifier: Programming Language :: Python :: 3
Classifier: Programming Language :: Python :: 3.4
Classifier: Programming Language :: Python :: 3.5
